inntinn/__init__.py
inntinn/api.py
inntinn/test___init__.py
inntinn-1.2.0.dist-info/LICENSE
inntinn-1.2.0.dist-info/METADATA
inntinn-1.2.0.dist-info/WHEEL
inntinn-1.2.0.dist-info/top_level.txt
inntinn-1.2.0.dist-info/RECORD
