Metadata-Version: 2.1
Name: inntinn
Version: 1.2.0
Summary: OSINT composite vulnerability database
Home-page: https://github.com/BlackburnHax/inntinn
Author: Brandon Blackburn
Author-email: contact@bhax.net
License: Apache License, Version 2.0
Platform: UNKNOWN
Classifier: Topic :: Security
Classifier: License :: OSI Approved :: Apache Software License
Classifier: Operating System :: MacOS :: MacOS X
Classifier: Operating System :: Microsoft :: Windows
Classifier: Operating System :: POSIX
Classifier: Programming Language :: Python
Classifier: Programming Language :: Python :: 3
Classifier: Programming Language :: Python :: 3 :: Only
Classifier: Natural Language :: English
Classifier: Topic :: Text Processing :: Markup :: reStructuredText
Classifier: Topic :: Database :: Database Engines/Servers
Requires-Dist: requests
Requires-Dist: mongoblack
Requires-Dist: sanic
Requires-Dist: blackburn
Requires-Dist: sanic-openapi
Requires-Dist: sanic-jwt
